silicone/__init__.py
silicone/_version.py
silicone/stats.py
silicone/utils.py
silicone/database_crunchers/__init__.py
silicone/database_crunchers/base.py
silicone/database_crunchers/constant_ratio.py
silicone/database_crunchers/equal_quantile_walk.py
silicone/database_crunchers/interpolate_specified_scenarios_and_models.py
silicone/database_crunchers/interpolation.py
silicone/database_crunchers/latest_time_ratio.py
silicone/database_crunchers/linear_interpolation.py
silicone/database_crunchers/quantile_rolling_windows.py
silicone/database_crunchers/rms_closest.py
silicone/database_crunchers/time_dep_quantile_rolling_windows.py
silicone/database_crunchers/time_dep_ratio.py
silicone/multiple_infillers/__init__.py
silicone/multiple_infillers/decompose_collection_with_time_dep_ratio.py
silicone/multiple_infillers/infill_all_required_emissions_for_openscm.py
silicone/multiple_infillers/infill_composite_values.py
silicone/multiple_infillers/split_collection_with_remainder_emissions.py
silicone/time_projectors/__init__.py
silicone/time_projectors/extend_latest_time_quantile.py
silicone/time_projectors/extend_rms_closest.py
silicone/time_projectors/linear_extender.py
silicone-1.3.0.dist-info/LICENSE
silicone-1.3.0.dist-info/METADATA
silicone-1.3.0.dist-info/WHEEL
silicone-1.3.0.dist-info/top_level.txt
silicone-1.3.0.dist-info/RECORD
