Metadata-Version: 2.1
Name: silicone
Version: 1.3.0
Summary: Automated filling of detail in reported emission scenarios
Home-page: https://github.com/GranthamImperial/silicone
Author: Robin Lamboll, Zebedee Nicholls, Jarmo Kikstra, Gaurav Ganti
Author-email: r.lamboll@imperial.ac.uk, zebedee.nicholls@climate-energy-college.org, kikstra@iiasa.ac.at, gaurav.ganti@climateanalytics.org
License: 3-Clause BSD License
Project-URL: Bug Reports, https://github.com/GranthamImperial/silicone/issues
Project-URL: Documentation, https://silicone.readthedocs.io/en/latest
Project-URL: Source, https://github.com/GranthamImperial/silicone
Keywords: emissions,automation,filling,detail,climate
Platform: UNKNOWN
Classifier: Development Status :: 3 - Alpha
Classifier: Intended Audience :: Developers
Classifier: License :: OSI Approved :: BSD License
Classifier: Programming Language :: Python :: 3.7
Classifier: Programming Language :: Python :: 3.8
Classifier: Programming Language :: Python :: 3.9
Requires-Dist: openscm-units (>=0.2)
Requires-Dist: pint
Requires-Dist: pyam-iamc (>=1.0.0)
Requires-Dist: python-dateutil
Requires-Dist: numpy
Requires-Dist: scipy
Requires-Dist: tqdm
Provides-Extra: deploy
Requires-Dist: setuptools (>=38.6.0) ; extra == 'deploy'
Requires-Dist: twine (>=1.11.0) ; extra == 'deploy'
Requires-Dist: wheel (>=0.31.0) ; extra == 'deploy'
Provides-Extra: dev
Requires-Dist: black ; extra == 'dev'
Requires-Dist: black-nb ; extra == 'dev'
Requires-Dist: bandit ; extra == 'dev'
Requires-Dist: coverage ; extra == 'dev'
Requires-Dist: flake8 ; extra == 'dev'
Requires-Dist: isort ; extra == 'dev'
Requires-Dist: mypy ; extra == 'dev'
Requires-Dist: nbdime ; extra == 'dev'
Requires-Dist: pydocstyle ; extra == 'dev'
Requires-Dist: pylint ; extra == 'dev'
Requires-Dist: notebook ; extra == 'dev'
Requires-Dist: seaborn ; extra == 'dev'
Requires-Dist: statsmodels ; extra == 'dev'
Requires-Dist: codecov ; extra == 'dev'
Requires-Dist: nbval ; extra == 'dev'
Requires-Dist: pytest ; extra == 'dev'
Requires-Dist: pytest-console-scripts ; extra == 'dev'
Requires-Dist: pytest-cov ; extra == 'dev'
Requires-Dist: sphinx (>2.1) ; extra == 'dev'
Requires-Dist: sphinx-rtd-theme ; extra == 'dev'
Requires-Dist: sphinx-autodoc-typehints ; extra == 'dev'
Requires-Dist: setuptools (>=38.6.0) ; extra == 'dev'
Requires-Dist: twine (>=1.11.0) ; extra == 'dev'
Requires-Dist: wheel (>=0.31.0) ; extra == 'dev'
Provides-Extra: docs
Requires-Dist: sphinx (>2.1) ; extra == 'docs'
Requires-Dist: sphinx-rtd-theme ; extra == 'docs'
Requires-Dist: sphinx-autodoc-typehints ; extra == 'docs'
Provides-Extra: notebooks
Requires-Dist: notebook ; extra == 'notebooks'
Requires-Dist: seaborn ; extra == 'notebooks'
Requires-Dist: statsmodels ; extra == 'notebooks'
Provides-Extra: tests
Requires-Dist: codecov ; extra == 'tests'
Requires-Dist: nbval ; extra == 'tests'
Requires-Dist: coverage ; extra == 'tests'
Requires-Dist: pytest ; extra == 'tests'
Requires-Dist: pytest-console-scripts ; extra == 'tests'
Requires-Dist: pytest-cov ; extra == 'tests'
